[{"id":166,"fighterId":166,"eventId":7,"opponentId":null,"opponent":"Myktybek Orolbai","fightDate":"Las Vegas, Nevada, U","result":"loss","methodCategory":"OTHER","methodDetail":null,"round":null,"timeInRound":null,"elapsedTimeSeconds":null,"promotion":"UFC","event":"UFC Fight Night: Emmett vs. Vallejos","referee":null,"weightClass":null,"notes":null,"createdAt":"2026-04-26 23:42:45","updatedAt":"2026-05-05 23:05:15"},{"id":878,"fighterId":166,"eventId":7,"opponentId":null,"opponent":"Myktybek Orolbai","fightDate":"2026-03-14","result":"loss","methodCategory":"DECISION","methodDetail":null,"round":3,"timeInRound":"05:00","elapsedTimeSeconds":900,"promotion":"UFC","event":"UFC Fight Night: Emmett vs. Vallejos","referee":null,"weightClass":null,"notes":null,"createdAt":"2026-04-26 23:45:19","updatedAt":"2026-05-05 23:05:15"},{"id":879,"fighterId":166,"eventId":219,"opponentId":null,"opponent":"Max Griffin","fightDate":"2025-07-12","result":"win","methodCategory":"DECISION","methodDetail":null,"round":3,"timeInRound":"05:00","elapsedTimeSeconds":900,"promotion":"UFC","event":"UFC Fight Night: Lewis vs. Teixeira","referee":null,"weightClass":null,"notes":null,"createdAt":"2026-04-26 23:45:19","updatedAt":"2026-05-05 23:05:15"},{"id":880,"fighterId":166,"eventId":279,"opponentId":null,"opponent":"Roman Kopylov","fightDate":"2025-01-11","result":"loss","methodCategory":"KO_TKO","methodDetail":null,"round":3,"timeInRound":"04:59","elapsedTimeSeconds":899,"promotion":"UFC","event":"UFC Fight Night: Dern vs. Ribas 2","referee":null,"weightClass":null,"notes":null,"createdAt":"2026-04-26 23:45:19","updatedAt":"2026-05-05 23:05:15"},{"id":881,"fighterId":166,"eventId":60,"opponentId":null,"opponent":"Brendan Allen","fightDate":"2024-04-06","result":"loss","methodCategory":"DECISION","methodDetail":null,"round":5,"timeInRound":"05:00","elapsedTimeSeconds":1500,"promotion":"UFC","event":"UFC Fight Night: Allen vs. Curtis 2","referee":null,"weightClass":null,"notes":null,"createdAt":"2026-04-26 23:45:19","updatedAt":"2026-05-05 23:05:15"},{"id":882,"fighterId":166,"eventId":205,"opponentId":null,"opponent":"Marc-Andre Barriault","fightDate":"2024-01-20","result":"win","methodCategory":"DECISION","methodDetail":null,"round":3,"timeInRound":"05:00","elapsedTimeSeconds":900,"promotion":"UFC","event":"UFC 297: Strickland vs. Du Plessis","referee":null,"weightClass":null,"notes":null,"createdAt":"2026-04-26 23:45:19","updatedAt":"2026-05-05 23:05:15"},{"id":883,"fighterId":166,"eventId":25,"opponentId":null,"opponent":"Nassourdine Imavov","fightDate":"2023-06-10","result":"no_contest","methodCategory":"OTHER","methodDetail":null,"round":2,"timeInRound":"03:04","elapsedTimeSeconds":484,"promotion":"UFC","event":"UFC 289: Nunes vs. Aldana","referee":null,"weightClass":null,"notes":null,"createdAt":"2026-04-26 23:45:19","updatedAt":"2026-05-05 23:05:15"},{"id":884,"fighterId":166,"eventId":34,"opponentId":null,"opponent":"Kelvin Gastelum","fightDate":"2023-04-08","result":"loss","methodCategory":"DECISION","methodDetail":null,"round":3,"timeInRound":"05:00","elapsedTimeSeconds":900,"promotion":"UFC","event":"UFC 287: Pereira vs. Adesanya 2","referee":null,"weightClass":null,"notes":null,"createdAt":"2026-04-26 23:45:19","updatedAt":"2026-05-05 23:05:15"},{"id":885,"fighterId":166,"eventId":63,"opponentId":null,"opponent":"Joaquin Buckley","fightDate":"2022-12-10","result":"win","methodCategory":"KO_TKO","methodDetail":null,"round":2,"timeInRound":"02:49","elapsedTimeSeconds":469,"promotion":"UFC","event":"UFC 282: Blachowicz vs. Ankalaev","referee":null,"weightClass":null,"notes":null,"createdAt":"2026-04-26 23:45:19","updatedAt":"2026-05-05 23:05:15"},{"id":886,"fighterId":166,"eventId":308,"opponentId":null,"opponent":"Jack Hermansson","fightDate":"2022-07-23","result":"loss","methodCategory":"DECISION","methodDetail":null,"round":3,"timeInRound":"05:00","elapsedTimeSeconds":900,"promotion":"UFC","event":"UFC Fight Night: Blaydes vs. Aspinall","referee":null,"weightClass":null,"notes":null,"createdAt":"2026-04-26 23:45:19","updatedAt":"2026-05-05 23:05:15"},{"id":887,"fighterId":166,"eventId":297,"opponentId":null,"opponent":"Rodolfo Vieira","fightDate":"2022-06-25","result":"win","methodCategory":"DECISION","methodDetail":null,"round":3,"timeInRound":"05:00","elapsedTimeSeconds":900,"promotion":"UFC","event":"UFC Fight Night: Tsarukyan vs. Gamrot","referee":null,"weightClass":null,"notes":null,"createdAt":"2026-04-26 23:45:19","updatedAt":"2026-05-05 23:05:15"},{"id":888,"fighterId":166,"eventId":64,"opponentId":null,"opponent":"Brendan Allen","fightDate":"2021-12-04","result":"win","methodCategory":"KO_TKO","methodDetail":null,"round":2,"timeInRound":"01:58","elapsedTimeSeconds":418,"promotion":"UFC","event":"UFC Fight Night: Font vs. Aldo","referee":null,"weightClass":null,"notes":null,"createdAt":"2026-04-26 23:45:19","updatedAt":"2026-05-05 23:05:15"},{"id":889,"fighterId":166,"eventId":347,"opponentId":null,"opponent":"Phil Hawes","fightDate":"2021-11-06","result":"win","methodCategory":"KO_TKO","methodDetail":null,"round":1,"timeInRound":"04:27","elapsedTimeSeconds":267,"promotion":"UFC","event":"UFC 268: Usman vs. Covington 2","referee":null,"weightClass":null,"notes":null,"createdAt":"2026-04-26 23:45:19","updatedAt":"2026-05-05 23:05:15"},{"id":890,"fighterId":166,"eventId":224,"opponentId":null,"opponent":"Sean Lally","fightDate":"2018-06-12","result":"win","methodCategory":"KO_TKO","methodDetail":null,"round":3,"timeInRound":"01:37","elapsedTimeSeconds":697,"promotion":"UFC","event":"DWCS 2.1","referee":null,"weightClass":null,"notes":null,"createdAt":"2026-04-26 23:45:19","updatedAt":"2026-05-05 23:05:15"}]