[{"id":181,"fighterId":181,"eventId":8,"opponentId":null,"opponent":"Max Holloway","fightDate":"Las Vegas, Nevada, U","result":"win","methodCategory":"OTHER","methodDetail":null,"round":null,"timeInRound":null,"elapsedTimeSeconds":null,"promotion":"UFC","event":"UFC 326: Holloway vs. Oliveira 2","referee":null,"weightClass":null,"notes":null,"createdAt":"2026-04-26 23:42:45","updatedAt":"2026-05-05 23:05:15"},{"id":809,"fighterId":181,"eventId":8,"opponentId":null,"opponent":"Max Holloway","fightDate":"2026-03-07","result":"win","methodCategory":"DECISION","methodDetail":null,"round":5,"timeInRound":"05:00","elapsedTimeSeconds":1500,"promotion":"UFC","event":"UFC 326: Holloway vs. Oliveira 2","referee":null,"weightClass":null,"notes":null,"createdAt":"2026-04-26 23:45:10","updatedAt":"2026-05-05 23:05:15"},{"id":810,"fighterId":181,"eventId":239,"opponentId":null,"opponent":"Mateusz Gamrot","fightDate":"2025-10-11","result":"win","methodCategory":"SUBMISSION","methodDetail":null,"round":2,"timeInRound":"02:48","elapsedTimeSeconds":468,"promotion":"UFC","event":"UFC Fight Night: Oliveira vs. Gamrot","referee":null,"weightClass":null,"notes":null,"createdAt":"2026-04-26 23:45:10","updatedAt":"2026-05-05 23:05:15"},{"id":811,"fighterId":181,"eventId":314,"opponentId":null,"opponent":"Ilia Topuria","fightDate":"2025-06-28","result":"loss","methodCategory":"KO_TKO","methodDetail":null,"round":1,"timeInRound":"02:27","elapsedTimeSeconds":147,"promotion":"UFC","event":"UFC 317: Topuria vs. Oliveira","referee":null,"weightClass":null,"notes":null,"createdAt":"2026-04-26 23:45:10","updatedAt":"2026-05-05 23:05:15"},{"id":812,"fighterId":181,"eventId":315,"opponentId":null,"opponent":"Michael Chandler","fightDate":"2024-11-16","result":"win","methodCategory":"DECISION","methodDetail":null,"round":5,"timeInRound":"05:00","elapsedTimeSeconds":1500,"promotion":"UFC","event":"UFC 309: Jones vs. Miocic","referee":null,"weightClass":null,"notes":null,"createdAt":"2026-04-26 23:45:10","updatedAt":"2026-05-05 23:05:15"},{"id":813,"fighterId":181,"eventId":135,"opponentId":null,"opponent":"Arman Tsarukyan","fightDate":"2024-04-13","result":"loss","methodCategory":"DECISION","methodDetail":null,"round":3,"timeInRound":"05:00","elapsedTimeSeconds":900,"promotion":"UFC","event":"UFC 300: Pereira vs. Hill","referee":null,"weightClass":null,"notes":null,"createdAt":"2026-04-26 23:45:10","updatedAt":"2026-05-05 23:05:15"},{"id":814,"fighterId":181,"eventId":25,"opponentId":null,"opponent":"Beneil Dariush","fightDate":"2023-06-10","result":"win","methodCategory":"KO_TKO","methodDetail":null,"round":1,"timeInRound":"04:10","elapsedTimeSeconds":250,"promotion":"UFC","event":"UFC 289: Nunes vs. Aldana","referee":null,"weightClass":null,"notes":null,"createdAt":"2026-04-26 23:45:10","updatedAt":"2026-05-05 23:05:15"},{"id":815,"fighterId":181,"eventId":138,"opponentId":null,"opponent":"Islam Makhachev","fightDate":"2022-10-22","result":"loss","methodCategory":"SUBMISSION","methodDetail":null,"round":2,"timeInRound":"03:16","elapsedTimeSeconds":496,"promotion":"UFC","event":"UFC 280: Oliveira vs. Makhachev","referee":null,"weightClass":null,"notes":null,"createdAt":"2026-04-26 23:45:10","updatedAt":"2026-05-05 23:05:15"},{"id":816,"fighterId":181,"eventId":316,"opponentId":null,"opponent":"Justin Gaethje","fightDate":"2022-05-07","result":"win","methodCategory":"SUBMISSION","methodDetail":null,"round":1,"timeInRound":"03:22","elapsedTimeSeconds":202,"promotion":"UFC","event":"UFC 274: Oliveira vs. Gaethje","referee":null,"weightClass":null,"notes":null,"createdAt":"2026-04-26 23:45:10","updatedAt":"2026-05-05 23:05:15"},{"id":817,"fighterId":181,"eventId":317,"opponentId":null,"opponent":"Dustin Poirier","fightDate":"2021-12-11","result":"win","methodCategory":"SUBMISSION","methodDetail":null,"round":3,"timeInRound":"01:02","elapsedTimeSeconds":662,"promotion":"UFC","event":"UFC 269: Oliveira vs. Poirier","referee":null,"weightClass":null,"notes":null,"createdAt":"2026-04-26 23:45:10","updatedAt":"2026-05-05 23:05:15"},{"id":818,"fighterId":181,"eventId":318,"opponentId":null,"opponent":"Michael Chandler","fightDate":"2021-05-15","result":"win","methodCategory":"KO_TKO","methodDetail":null,"round":2,"timeInRound":"00:19","elapsedTimeSeconds":319,"promotion":"UFC","event":"UFC 262: Oliveira vs. Chandler","referee":null,"weightClass":null,"notes":null,"createdAt":"2026-04-26 23:45:10","updatedAt":"2026-05-05 23:05:15"},{"id":819,"fighterId":181,"eventId":268,"opponentId":null,"opponent":"Tony Ferguson","fightDate":"2020-12-12","result":"win","methodCategory":"DECISION","methodDetail":null,"round":3,"timeInRound":"05:00","elapsedTimeSeconds":900,"promotion":"UFC","event":"UFC 256: Figueiredo vs. Moreno","referee":null,"weightClass":null,"notes":null,"createdAt":"2026-04-26 23:45:10","updatedAt":"2026-05-05 23:05:15"},{"id":820,"fighterId":181,"eventId":269,"opponentId":null,"opponent":"Kevin Lee","fightDate":"2020-03-14","result":"win","methodCategory":"SUBMISSION","methodDetail":null,"round":3,"timeInRound":"00:28","elapsedTimeSeconds":628,"promotion":"UFC","event":"UFC Fight Night: Lee vs. Oliveira","referee":null,"weightClass":null,"notes":null,"createdAt":"2026-04-26 23:45:10","updatedAt":"2026-05-05 23:05:15"},{"id":821,"fighterId":181,"eventId":319,"opponentId":null,"opponent":"Jared Gordon","fightDate":"2019-11-16","result":"win","methodCategory":"KO_TKO","methodDetail":null,"round":1,"timeInRound":"01:26","elapsedTimeSeconds":86,"promotion":"UFC","event":"UFC Fight Night: Blachowicz vs. Jacare","referee":null,"weightClass":null,"notes":null,"createdAt":"2026-04-26 23:45:10","updatedAt":"2026-05-05 23:05:15"},{"id":822,"fighterId":181,"eventId":313,"opponentId":null,"opponent":"Nik Lentz","fightDate":"2019-05-18","result":"win","methodCategory":"KO_TKO","methodDetail":null,"round":2,"timeInRound":"02:11","elapsedTimeSeconds":431,"promotion":"UFC","event":"UFC Fight Night: Dos Anjos vs. Lee","referee":null,"weightClass":null,"notes":null,"createdAt":"2026-04-26 23:45:10","updatedAt":"2026-05-05 23:05:15"},{"id":823,"fighterId":181,"eventId":198,"opponentId":null,"opponent":"David Teymur","fightDate":"2019-02-02","result":"win","methodCategory":"SUBMISSION","methodDetail":null,"round":2,"timeInRound":"00:55","elapsedTimeSeconds":355,"promotion":"UFC","event":"UFC Fight Night: Assuncao vs. Moraes 2","referee":null,"weightClass":null,"notes":null,"createdAt":"2026-04-26 23:45:10","updatedAt":"2026-05-05 23:05:15"},{"id":824,"fighterId":181,"eventId":320,"opponentId":null,"opponent":"Jim Miller","fightDate":"2018-12-15","result":"win","methodCategory":"SUBMISSION","methodDetail":null,"round":1,"timeInRound":"01:15","elapsedTimeSeconds":75,"promotion":"UFC","event":"UFC Fight Night: Lee vs. Iaquinta","referee":null,"weightClass":null,"notes":null,"createdAt":"2026-04-26 23:45:10","updatedAt":"2026-05-05 23:05:15"},{"id":825,"fighterId":181,"eventId":321,"opponentId":null,"opponent":"Christos Giagos","fightDate":"2018-09-22","result":"win","methodCategory":"SUBMISSION","methodDetail":null,"round":2,"timeInRound":"03:22","elapsedTimeSeconds":502,"promotion":"UFC","event":"UFC Fight Night: Marreta vs. Anders","referee":null,"weightClass":null,"notes":null,"createdAt":"2026-04-26 23:45:10","updatedAt":"2026-05-05 23:05:15"},{"id":826,"fighterId":181,"eventId":322,"opponentId":null,"opponent":"Clay Guida","fightDate":"2018-06-09","result":"win","methodCategory":"SUBMISSION","methodDetail":null,"round":1,"timeInRound":"02:18","elapsedTimeSeconds":138,"promotion":"UFC","event":"UFC 225: Whittaker vs. Romero 2","referee":null,"weightClass":null,"notes":null,"createdAt":"2026-04-26 23:45:10","updatedAt":"2026-05-05 23:05:15"},{"id":827,"fighterId":181,"eventId":323,"opponentId":null,"opponent":"Paul Felder","fightDate":"2017-12-02","result":"loss","methodCategory":"KO_TKO","methodDetail":null,"round":2,"timeInRound":"04:06","elapsedTimeSeconds":546,"promotion":"UFC","event":"UFC 218: Holloway vs. Aldo 2","referee":null,"weightClass":null,"notes":null,"createdAt":"2026-04-26 23:45:10","updatedAt":"2026-05-05 23:05:15"},{"id":828,"fighterId":181,"eventId":324,"opponentId":null,"opponent":"Will Brooks","fightDate":"2017-04-08","result":"win","methodCategory":"SUBMISSION","methodDetail":null,"round":1,"timeInRound":"02:30","elapsedTimeSeconds":150,"promotion":"UFC","event":"UFC 210: Cormier vs. Johnson 2","referee":null,"weightClass":null,"notes":null,"createdAt":"2026-04-26 23:45:10","updatedAt":"2026-05-05 23:05:15"},{"id":829,"fighterId":181,"eventId":101,"opponentId":null,"opponent":"Ricardo Lamas","fightDate":"2016-11-05","result":"loss","methodCategory":"SUBMISSION","methodDetail":null,"round":2,"timeInRound":"02:13","elapsedTimeSeconds":433,"promotion":"UFC","event":"UFC Fight Night: Dos Anjos vs. Ferguson","referee":null,"weightClass":null,"notes":null,"createdAt":"2026-04-26 23:45:10","updatedAt":"2026-05-05 23:05:15"},{"id":830,"fighterId":181,"eventId":325,"opponentId":null,"opponent":"Anthony Pettis","fightDate":"2016-08-27","result":"loss","methodCategory":"SUBMISSION","methodDetail":null,"round":3,"timeInRound":"01:49","elapsedTimeSeconds":709,"promotion":"UFC","event":"UFC on FOX: Maia vs. Condit","referee":null,"weightClass":null,"notes":null,"createdAt":"2026-04-26 23:45:10","updatedAt":"2026-05-05 23:05:15"},{"id":831,"fighterId":181,"eventId":326,"opponentId":null,"opponent":"Myles Jury","fightDate":"2015-12-19","result":"win","methodCategory":"SUBMISSION","methodDetail":null,"round":1,"timeInRound":"03:05","elapsedTimeSeconds":185,"promotion":"UFC","event":"UFC on FOX: Dos Anjos vs. Cowboy 2","referee":null,"weightClass":null,"notes":null,"createdAt":"2026-04-26 23:45:10","updatedAt":"2026-05-05 23:05:15"},{"id":832,"fighterId":181,"eventId":327,"opponentId":null,"opponent":"Max Holloway","fightDate":"2015-08-23","result":"loss","methodCategory":"KO_TKO","methodDetail":null,"round":1,"timeInRound":"01:39","elapsedTimeSeconds":99,"promotion":"UFC","event":"UFC Fight Night: Holloway vs Oliveira","referee":null,"weightClass":null,"notes":null,"createdAt":"2026-04-26 23:45:10","updatedAt":"2026-05-05 23:05:15"},{"id":833,"fighterId":181,"eventId":328,"opponentId":null,"opponent":"Nik Lentz","fightDate":"2015-05-30","result":"win","methodCategory":"SUBMISSION","methodDetail":null,"round":3,"timeInRound":"01:10","elapsedTimeSeconds":670,"promotion":"UFC","event":"UFC Fight Night: Condit vs Alves","referee":null,"weightClass":null,"notes":null,"createdAt":"2026-04-26 23:45:10","updatedAt":"2026-05-05 23:05:15"},{"id":834,"fighterId":181,"eventId":329,"opponentId":null,"opponent":"Jeremy Stephens","fightDate":"2014-12-12","result":"win","methodCategory":"DECISION","methodDetail":null,"round":3,"timeInRound":"05:00","elapsedTimeSeconds":900,"promotion":"UFC","event":"The Ultimate Fighter: A Champion Will Be Crowned Finale","referee":null,"weightClass":null,"notes":null,"createdAt":"2026-04-26 23:45:10","updatedAt":"2026-05-05 23:05:15"},{"id":835,"fighterId":181,"eventId":330,"opponentId":null,"opponent":"Hatsu Hioki","fightDate":"2014-06-28","result":"win","methodCategory":"SUBMISSION","methodDetail":null,"round":2,"timeInRound":"04:32","elapsedTimeSeconds":572,"promotion":"UFC","event":"UFC Fight Night: Te Huna vs Marquardt","referee":null,"weightClass":null,"notes":null,"createdAt":"2026-04-26 23:45:10","updatedAt":"2026-05-05 23:05:15"},{"id":836,"fighterId":181,"eventId":331,"opponentId":null,"opponent":"Andy Ogle","fightDate":"2014-02-15","result":"win","methodCategory":"SUBMISSION","methodDetail":null,"round":3,"timeInRound":"02:40","elapsedTimeSeconds":760,"promotion":"UFC","event":"UFC Fight Night: Machida vs Mousasi","referee":null,"weightClass":null,"notes":null,"createdAt":"2026-04-26 23:45:10","updatedAt":"2026-05-05 23:05:15"},{"id":837,"fighterId":181,"eventId":332,"opponentId":null,"opponent":"Frankie Edgar","fightDate":"2013-07-06","result":"loss","methodCategory":"DECISION","methodDetail":null,"round":3,"timeInRound":"05:00","elapsedTimeSeconds":900,"promotion":"UFC","event":"UFC 162: Silva vs Weidman","referee":null,"weightClass":null,"notes":null,"createdAt":"2026-04-26 23:45:10","updatedAt":"2026-05-05 23:05:15"},{"id":838,"fighterId":181,"eventId":333,"opponentId":null,"opponent":"Cub Swanson","fightDate":"2012-09-22","result":"loss","methodCategory":"KO_TKO","methodDetail":null,"round":1,"timeInRound":"02:40","elapsedTimeSeconds":160,"promotion":"UFC","event":"UFC 152: Jones vs Belfort","referee":null,"weightClass":null,"notes":null,"createdAt":"2026-04-26 23:45:10","updatedAt":"2026-05-05 23:05:15"},{"id":839,"fighterId":181,"eventId":334,"opponentId":null,"opponent":"Jonathan Brookins","fightDate":"2012-06-01","result":"win","methodCategory":"SUBMISSION","methodDetail":null,"round":2,"timeInRound":"02:42","elapsedTimeSeconds":462,"promotion":"UFC","event":"The Ultimate Fighter: Live Finale","referee":null,"weightClass":null,"notes":null,"createdAt":"2026-04-26 23:45:10","updatedAt":"2026-05-05 23:05:15"},{"id":840,"fighterId":181,"eventId":335,"opponentId":null,"opponent":"Eric Wisely","fightDate":"2012-01-28","result":"win","methodCategory":"SUBMISSION","methodDetail":null,"round":1,"timeInRound":"01:43","elapsedTimeSeconds":103,"promotion":"UFC","event":"UFC on FOX: Evans vs Davis","referee":null,"weightClass":null,"notes":null,"createdAt":"2026-04-26 23:45:10","updatedAt":"2026-05-05 23:05:15"},{"id":841,"fighterId":181,"eventId":336,"opponentId":null,"opponent":"Donald Cerrone","fightDate":"2011-08-14","result":"loss","methodCategory":"KO_TKO","methodDetail":null,"round":1,"timeInRound":"03:01","elapsedTimeSeconds":181,"promotion":"UFC","event":"UFC Live: Hardy vs Lytle","referee":null,"weightClass":null,"notes":null,"createdAt":"2026-04-26 23:45:10","updatedAt":"2026-05-05 23:05:15"},{"id":842,"fighterId":181,"eventId":337,"opponentId":null,"opponent":"Nik Lentz","fightDate":"2011-06-26","result":"no_contest","methodCategory":"OTHER","methodDetail":null,"round":2,"timeInRound":"01:48","elapsedTimeSeconds":408,"promotion":"UFC","event":"UFC Live: Kongo vs Barry","referee":null,"weightClass":null,"notes":null,"createdAt":"2026-04-26 23:45:10","updatedAt":"2026-05-05 23:05:15"},{"id":843,"fighterId":181,"eventId":338,"opponentId":null,"opponent":"Jim Miller","fightDate":"2010-12-11","result":"loss","methodCategory":"SUBMISSION","methodDetail":null,"round":1,"timeInRound":"01:59","elapsedTimeSeconds":119,"promotion":"UFC","event":"UFC 124: St-Pierre vs Koscheck 2","referee":null,"weightClass":null,"notes":null,"createdAt":"2026-04-26 23:45:10","updatedAt":"2026-05-05 23:05:15"},{"id":844,"fighterId":181,"eventId":339,"opponentId":null,"opponent":"Efrain Escudero","fightDate":"2010-09-15","result":"win","methodCategory":"SUBMISSION","methodDetail":null,"round":3,"timeInRound":"02:25","elapsedTimeSeconds":745,"promotion":"UFC","event":"UFC Fight Night: Marquardt vs Palhares","referee":null,"weightClass":null,"notes":null,"createdAt":"2026-04-26 23:45:10","updatedAt":"2026-05-05 23:05:15"},{"id":845,"fighterId":181,"eventId":340,"opponentId":null,"opponent":"Darren Elkins","fightDate":"2010-08-01","result":"win","methodCategory":"SUBMISSION","methodDetail":null,"round":1,"timeInRound":"00:41","elapsedTimeSeconds":41,"promotion":"UFC","event":"UFC Live: Jones vs Matyushenko","referee":null,"weightClass":null,"notes":null,"createdAt":"2026-04-26 23:45:10","updatedAt":"2026-05-05 23:05:15"}]