[{"id":243,"fighterId":241,"eventId":10,"opponentId":null,"opponent":"Chidi Njokuani","fightDate":"Houston, Texas, USA","result":"win","methodCategory":"OTHER","methodDetail":null,"round":null,"timeInRound":null,"elapsedTimeSeconds":null,"promotion":"UFC","event":"UFC Fight Night: Strickland vs. Hernandez","referee":null,"weightClass":null,"notes":null,"createdAt":"2026-04-26 23:42:46","updatedAt":"2026-05-05 23:05:15"},{"id":754,"fighterId":241,"eventId":10,"opponentId":null,"opponent":"Chidi Njokuani","fightDate":"2026-02-21","result":"win","methodCategory":"DECISION","methodDetail":null,"round":3,"timeInRound":"05:00","elapsedTimeSeconds":900,"promotion":"UFC","event":"UFC Fight Night: Strickland vs. Hernandez","referee":null,"weightClass":null,"notes":null,"createdAt":"2026-04-26 23:44:59","updatedAt":"2026-05-05 23:05:15"},{"id":755,"fighterId":241,"eventId":240,"opponentId":null,"opponent":"Muslim Salikhov","fightDate":"2025-07-26","result":"loss","methodCategory":"KO_TKO","methodDetail":null,"round":1,"timeInRound":"00:42","elapsedTimeSeconds":42,"promotion":"UFC","event":"UFC Fight Night: Whittaker vs. De Ridder","referee":null,"weightClass":null,"notes":null,"createdAt":"2026-04-26 23:44:59","updatedAt":"2026-05-05 23:05:15"},{"id":756,"fighterId":241,"eventId":58,"opponentId":null,"opponent":"Alex Morono","fightDate":"2025-03-08","result":"win","methodCategory":"KO_TKO","methodDetail":null,"round":1,"timeInRound":"04:16","elapsedTimeSeconds":256,"promotion":"UFC","event":"UFC 313: Pereira vs. Ankalaev","referee":null,"weightClass":null,"notes":null,"createdAt":"2026-04-26 23:44:59","updatedAt":"2026-05-05 23:05:15"},{"id":757,"fighterId":241,"eventId":276,"opponentId":null,"opponent":"Rinat Fakhretdinov","fightDate":"2024-10-26","result":"loss","methodCategory":"DECISION","methodDetail":null,"round":3,"timeInRound":"05:00","elapsedTimeSeconds":900,"promotion":"UFC","event":"UFC 308: Topuria vs. Holloway","referee":null,"weightClass":null,"notes":null,"createdAt":"2026-04-26 23:44:59","updatedAt":"2026-05-05 23:05:15"}]