[{"id":73,"fighterId":73,"eventId":3,"opponentId":null,"opponent":"Francisco Prado","fightDate":"Miami, Florida, USA","result":"win","methodCategory":"OTHER","methodDetail":null,"round":null,"timeInRound":null,"elapsedTimeSeconds":null,"promotion":"UFC","event":"UFC 327: Prochazka vs. Ulberg","referee":null,"weightClass":null,"notes":null,"createdAt":"2026-04-26 23:42:44","updatedAt":"2026-05-05 23:05:15"},{"id":846,"fighterId":73,"eventId":3,"opponentId":null,"opponent":"Francisco Prado","fightDate":"2026-04-11","result":"win","methodCategory":"DECISION","methodDetail":null,"round":3,"timeInRound":"05:00","elapsedTimeSeconds":900,"promotion":"UFC","event":"UFC 327: Prochazka vs. Ulberg","referee":null,"weightClass":null,"notes":null,"createdAt":"2026-04-26 23:45:12","updatedAt":"2026-05-05 23:05:15"},{"id":847,"fighterId":73,"eventId":192,"opponentId":null,"opponent":"Daniel Frunza","fightDate":"2025-11-01","result":"win","methodCategory":"SUBMISSION","methodDetail":null,"round":3,"timeInRound":"04:29","elapsedTimeSeconds":869,"promotion":"UFC","event":"UFC Fight Night: Garcia vs. Onama","referee":null,"weightClass":null,"notes":null,"createdAt":"2026-04-26 23:45:12","updatedAt":"2026-05-05 23:05:15"},{"id":848,"fighterId":73,"eventId":89,"opponentId":null,"opponent":"Mike Malott","fightDate":"2025-05-10","result":"loss","methodCategory":"KO_TKO","methodDetail":null,"round":2,"timeInRound":"00:26","elapsedTimeSeconds":326,"promotion":"UFC","event":"UFC 315: Muhammad vs. Della Maddalena","referee":null,"weightClass":null,"notes":null,"createdAt":"2026-04-26 23:45:12","updatedAt":"2026-05-05 23:05:15"},{"id":849,"fighterId":73,"eventId":201,"opponentId":null,"opponent":"Matthew Semelsberger","fightDate":"2024-11-09","result":"win","methodCategory":"KO_TKO","methodDetail":null,"round":1,"timeInRound":"00:51","elapsedTimeSeconds":51,"promotion":"UFC","event":"UFC Fight Night: Magny vs. Prates","referee":null,"weightClass":null,"notes":null,"createdAt":"2026-04-26 23:45:12","updatedAt":"2026-05-05 23:05:15"},{"id":850,"fighterId":73,"eventId":277,"opponentId":null,"opponent":"Carlos Prates","fightDate":"2024-06-08","result":"loss","methodCategory":"KO_TKO","methodDetail":null,"round":1,"timeInRound":"04:47","elapsedTimeSeconds":287,"promotion":"UFC","event":"UFC Fight Night: Cannonier vs. Imavov","referee":null,"weightClass":null,"notes":null,"createdAt":"2026-04-26 23:45:12","updatedAt":"2026-05-05 23:05:15"},{"id":851,"fighterId":73,"eventId":304,"opponentId":null,"opponent":"Gilbert Urbina","fightDate":"2024-02-03","result":"win","methodCategory":"KO_TKO","methodDetail":null,"round":1,"timeInRound":"04:47","elapsedTimeSeconds":287,"promotion":"UFC","event":"UFC Fight Night: Dolidze vs. Imavov","referee":null,"weightClass":null,"notes":null,"createdAt":"2026-04-26 23:45:12","updatedAt":"2026-05-05 23:05:15"},{"id":852,"fighterId":73,"eventId":221,"opponentId":null,"opponent":"Blood Diamond","fightDate":"2023-09-09","result":"win","methodCategory":"DECISION","methodDetail":null,"round":3,"timeInRound":"05:00","elapsedTimeSeconds":900,"promotion":"UFC","event":"UFC 293: Adesanya vs. Strickland","referee":null,"weightClass":null,"notes":null,"createdAt":"2026-04-26 23:45:12","updatedAt":"2026-05-05 23:05:15"}]