{"id":105,"externalId":"http://ufcstats.com/fighter-details/c58f51dedb310998","name":"Michael Chiesa","nickname":"Maverick","nationality":"United States","birthDate":"Dec 07, 1987","age":null,"heightCm":185.4,"reachCm":190.5,"weightKg":77.1,"stance":"Southpaw","primaryTeam":null,"weightClass":"Welterweight","sourceUrl":"http://ufcstats.com/fighter-details/c58f51dedb310998","sourceOrg":null,"lastScrapedAt":"2026-04-29 02:34:04","primaryBases":null,"styleArchetype":"Grappler","strengths":"[\"Jogo de chão e finalizações (56% das vitórias)\", \"Sequência de 5 vitórias consecutivas — momento positivo\"]","weaknesses":"[\"Defesa no chão questionável — finalizado 5 vezes\"]","howHeWins":"[\"Finalização (9 vitórias)\", \"Decisão dos juízes (6 vitórias)\"]","howHeLoses":"[\"Vulnerável ao nocaute (1 derrota)\", \"Vulnerável a finalizações (5 derrotas)\", \"Pode perder no volume e nos pontos (1 derrota)\"]","totalFightsPro":23,"wins":16,"losses":7,"draws":0,"winRate":0.6957,"finishRate":0.5625,"submissionWinRate":0.5625,"koTkoWins":0,"submissionWins":9,"decisionWins":6,"currentStreak":"W","currentStreakCount":5,"longestWinStreak":5,"avgFightTimeSeconds":552.682,"createdAt":"2026-04-26 23:34:37","updatedAt":"2026-05-04 19:07:42","isChampion":0,"isInterim":0}