{"id":1446,"externalId":"ufc-7ae36b3791e0969a","name":"Shannon Clark","nickname":"MMA Barbie","nationality":"United States","birthDate":"Jul 07, 1992","age":null,"heightCm":null,"reachCm":162.6,"weightKg":56.7,"stance":"Orthodox","primaryTeam":"","weightClass":"Women's Flyweight","sourceUrl":"https://www.sherdog.com/fighter/Shannon-Clark-316313","sourceOrg":"LFA","lastScrapedAt":"2026-05-03 06:19:39","primaryBases":null,"styleArchetype":null,"strengths":null,"weaknesses":null,"howHeWins":null,"howHeLoses":null,"totalFightsPro":8,"wins":4,"losses":4,"draws":0,"winRate":0.5,"finishRate":0.5,"submissionWinRate":0.0,"koTkoWins":2,"submissionWins":0,"decisionWins":2,"currentStreak":null,"currentStreakCount":0,"longestWinStreak":0,"avgFightTimeSeconds":null,"createdAt":"2026-04-29 00:17:48","updatedAt":"2026-05-07 06:17:37","isChampion":1,"isInterim":0}