{"id":241,"externalId":"http://ufcstats.com/fighter-details/28d421729451c8ca","name":"Carlos Leal","nickname":"The Lion","nationality":"Brazil","birthDate":"May 04, 1994","age":null,"heightCm":180.3,"reachCm":188.0,"weightKg":77.1,"stance":"Orthodox","primaryTeam":null,"weightClass":"Welterweight","sourceUrl":"http://ufcstats.com/fighter-details/28d421729451c8ca","sourceOrg":null,"lastScrapedAt":"2026-04-29 02:38:57","primaryBases":null,"styleArchetype":"All-Around","strengths":"[\"Experiência profissional consistente\"]","weaknesses":"[\"Histórico de derrotas aponta para pontos a desenvolver\"]","howHeWins":"[\"KO/TKO (1 vitória)\", \"Decisão dos juízes (1 vitória)\"]","howHeLoses":"[\"Vulnerável ao nocaute (1 derrota)\", \"Pode perder no volume e nos pontos (1 derrota)\"]","totalFightsPro":5,"wins":3,"losses":2,"draws":0,"winRate":0.6,"finishRate":0.3333,"submissionWinRate":0.0,"koTkoWins":1,"submissionWins":0,"decisionWins":1,"currentStreak":"W","currentStreakCount":2,"longestWinStreak":2,"avgFightTimeSeconds":524.5,"createdAt":"2026-04-26 23:39:43","updatedAt":"2026-05-04 19:44:47","isChampion":0,"isInterim":0}