{"id":2413,"externalId":"http://ufcstats.com/fighter-details/5444c5a201d3ee5a","name":"Jamahal Hill","nickname":"Sweet Dreams","nationality":"United States","birthDate":"May 19, 1991","age":null,"heightCm":193.0,"reachCm":236.2,"weightKg":93.0,"stance":"Southpaw","primaryTeam":"","weightClass":"Light Heavyweight","sourceUrl":"http://ufcstats.com/fighter-details/5444c5a201d3ee5a","sourceOrg":"UFC","lastScrapedAt":"2026-04-29 00:55:05","primaryBases":null,"styleArchetype":null,"strengths":null,"weaknesses":null,"howHeWins":null,"howHeLoses":null,"totalFightsPro":12,"wins":7,"losses":4,"draws":0,"winRate":0.583333,"finishRate":0.714286,"submissionWinRate":0.0,"koTkoWins":5,"submissionWins":0,"decisionWins":2,"currentStreak":null,"currentStreakCount":0,"longestWinStreak":0,"avgFightTimeSeconds":null,"createdAt":"2026-04-29 00:55:05","updatedAt":"2026-05-04 19:25:18","isChampion":0,"isInterim":0}