{"id":4895,"externalId":"sherdog-Oumar-Kane-350661","name":"Oumar Kane","nickname":null,"nationality":"Senegal","birthDate":"Mar 14, 1992","age":null,"heightCm":193.0,"reachCm":null,"weightKg":120.2,"stance":null,"primaryTeam":"971 MMA","weightClass":"Heavyweight","sourceUrl":"https://www.sherdog.com/fighter/Oumar-Kane-350661","sourceOrg":"ONE Championship","lastScrapedAt":"2026-05-03 06:20:13","primaryBases":null,"styleArchetype":null,"strengths":null,"weaknesses":null,"howHeWins":null,"howHeLoses":null,"totalFightsPro":16,"wins":14,"losses":2,"draws":0,"winRate":0.875,"finishRate":0.571429,"submissionWinRate":0.0,"koTkoWins":8,"submissionWins":0,"decisionWins":6,"currentStreak":null,"currentStreakCount":0,"longestWinStreak":0,"avgFightTimeSeconds":null,"createdAt":"2026-04-29 15:34:49","updatedAt":"2026-05-04 06:17:21","isChampion":0,"isInterim":0}