{"id":590,"externalId":"ufc-d31a5546c0e9b213","name":"Rodrigo Nascimento","nickname":"Ze Colmeia","nationality":"Brazil","birthDate":"Nov 26, 1992","age":null,"heightCm":null,"reachCm":203.2,"weightKg":null,"stance":"Orthodox","primaryTeam":"","weightClass":"Heavyweight","sourceUrl":null,"sourceOrg":"PFL","lastScrapedAt":"2026-04-28 20:29:59","primaryBases":null,"styleArchetype":null,"strengths":null,"weaknesses":null,"howHeWins":null,"howHeLoses":null,"totalFightsPro":1,"wins":0,"losses":1,"draws":0,"winRate":0.0,"finishRate":0.0,"submissionWinRate":0.0,"koTkoWins":0,"submissionWins":0,"decisionWins":0,"currentStreak":"L","currentStreakCount":1,"longestWinStreak":0,"avgFightTimeSeconds":null,"createdAt":"2026-04-28 20:29:59","updatedAt":"2026-05-04 20:52:35","isChampion":0,"isInterim":0}