{"id":730,"externalId":null,"name":"Jameson Pantoja Reis","nickname":"","nationality":"Brazil","birthDate":"","age":null,"heightCm":null,"reachCm":null,"weightKg":null,"stance":"","primaryTeam":"","weightClass":"Welterweight","sourceUrl":null,"sourceOrg":"LFA","lastScrapedAt":"2026-04-28 23:51:40","primaryBases":null,"styleArchetype":null,"strengths":null,"weaknesses":null,"howHeWins":null,"howHeLoses":null,"totalFightsPro":3,"wins":3,"losses":0,"draws":0,"winRate":1.0,"finishRate":1.0,"submissionWinRate":1.0,"koTkoWins":0,"submissionWins":3,"decisionWins":0,"currentStreak":"W","currentStreakCount":3,"longestWinStreak":3,"avgFightTimeSeconds":null,"createdAt":"2026-04-28 23:51:40","updatedAt":"2026-05-04 19:50:05","isChampion":0,"isInterim":0}