{"id":934,"externalId":"http://ufcstats.com/fighter-details/399afbabc02376b5","name":"Tom Aspinall","nickname":"","nationality":"England","birthDate":"Apr 11, 1993","age":null,"heightCm":195.6,"reachCm":233.7,"weightKg":115.7,"stance":"Orthodox","primaryTeam":"","weightClass":"Men's P4P","sourceUrl":"http://ufcstats.com/fighter-details/399afbabc02376b5","sourceOrg":"UFC","lastScrapedAt":"2026-04-28 23:58:08","primaryBases":null,"styleArchetype":null,"strengths":null,"weaknesses":null,"howHeWins":null,"howHeLoses":null,"totalFightsPro":10,"wins":8,"losses":1,"draws":0,"winRate":0.8,"finishRate":1.0,"submissionWinRate":0.25,"koTkoWins":6,"submissionWins":2,"decisionWins":0,"currentStreak":null,"currentStreakCount":0,"longestWinStreak":0,"avgFightTimeSeconds":null,"createdAt":"2026-04-28 23:58:08","updatedAt":"2026-05-07 06:17:37","isChampion":1,"isInterim":0}